MANIFEST.in
README.md
README.rst
setup.py
pyorient/__init__.py
pyorient/constants.py
pyorient/exceptions.py
pyorient/groovy.py
pyorient/hexdump.py
pyorient/orient.py
pyorient/otypes.py
pyorient/scripts.py
pyorient/serializations.py
pyorient/utils.py
pyorient.egg-info/PKG-INFO
pyorient.egg-info/SOURCES.txt
pyorient.egg-info/dependency_links.txt
pyorient.egg-info/top_level.txt
pyorient/messages/__init__.py
pyorient/messages/base.py
pyorient/messages/cluster.py
pyorient/messages/commands.py
pyorient/messages/connection.py
pyorient/messages/database.py
pyorient/messages/records.py
pyorient/ogm/__init__.py
pyorient/ogm/batch.py
pyorient/ogm/broker.py
pyorient/ogm/commands.py
pyorient/ogm/config.py
pyorient/ogm/declarative.py
pyorient/ogm/edge.py
pyorient/ogm/element.py
pyorient/ogm/exceptions.py
pyorient/ogm/graph.py
pyorient/ogm/operators.py
pyorient/ogm/property.py
pyorient/ogm/query.py
pyorient/ogm/query_utils.py
pyorient/ogm/vertex.py
pyorient/ogm/what.py