Metadata-Version: 1.0
Name: pyorient
Version: 1.5.5
Summary: OrientDB native client library
Home-page: UNKNOWN
Author: Niko Usai <mogui83@gmail.com>, Domenico Lupinetti <ostico@gmail.com>
Author-email: UNKNOWN
License: LICENSE
Platform: UNKNOWN
